LICENSE
README.md
pyproject.toml
gamda/__init__.py
gamda/core.py
gamda/cudasrc.py
gamda.egg-info/PKG-INFO
gamda.egg-info/SOURCES.txt
gamda.egg-info/dependency_links.txt
gamda.egg-info/requires.txt
gamda.egg-info/top_level.txt
gamda/analyzer/__init__.py
gamda/analyzer/trajectory_analyzer.py
gamda/observable/__init__.py
gamda/observable/cupy_observable.py
gamda/observable/listed_observable.py
gamda/observable/pairwise_observable.py