Metadata-Version: 2.1
Name: gamda
Version: 0.5
Summary: gamda: GPU-Accelerated Molecular Dynamics Analysis
Author-email: Yijie Xia <yijiexia@pku.edu.cn>
License: ##############################################################################
Keywords: SPONGE,molecular dynamics
Classifier: Development Status :: 5 - Production/Stable
Classifier: Environment :: GPU :: NVIDIA CUDA
Classifier: Environment :: Plugins
Classifier: License :: OSI Approved :: Apache Software License
Classifier: Topic :: Scientific/Engineering :: Physics
Classifier: Topic :: Scientific/Engineering :: Chemistry
Classifier: Programming Language :: Python :: 3
Classifier: Operating System :: POSIX :: Linux
Classifier: Operating System :: Microsoft :: Windows
License-File: LICENSE
Requires-Dist: MDAnalysis
